bvqpy/__init__.py
bvqpy/connect.py
bvqpy/participants.py
bvqpy-0.0.1.2.dist-info/LICENSE
bvqpy-0.0.1.2.dist-info/METADATA
bvqpy-0.0.1.2.dist-info/WHEEL
bvqpy-0.0.1.2.dist-info/top_level.txt
bvqpy-0.0.1.2.dist-info/RECORD
