Metadata-Version: 2.1
Name: bvqpy
Version: 0.0.1.2
Summary: Barcelona Vocabulary Questonnaire
Home-page: https://github.com/gongcastro/bvqpy
Author: Gonzalo Garcia-Castro
Author-email: gongarciacastro@gmail.com
Project-URL: Bug Reports, https://github.com/gongcastro/bvqpy/issues
Project-URL: Source, https://github.com/gongcastro/bvqpy/
Keywords: python,vocabulary
Classifier: Development Status :: 1 - Planning
Classifier: Intended Audience :: Science/Research
Classifier: License :: OSI Approved :: MIT License
Classifier: Programming Language :: Python :: 3
Classifier: Operating System :: MacOS :: MacOS X
Classifier: Operating System :: POSIX :: Linux
Classifier: Operating System :: Microsoft :: Windows
Requires-Python: >=3.7
License-File: LICENSE
Requires-Dist: requests
Requires-Dist: pandas
Requires-Dist: numpy
